fav_stock/__init__.py
fav_stock/admin.py
fav_stock/apps.py
fav_stock/models.py
fav_stock/tests.py
fav_stock/urls.py
fav_stock/views.py
fav_stock/migrations/0001_initial.py
fav_stock/migrations/__init__.py
fav_stock/templates/fav_stock/add_n_edit_fav.html
fav_stock/templates/fav_stock/del_fav.html
fav_stock/templates/fav_stock/test.html
fav_stock/templatetags/__init__.py
fav_stock/templatetags/fav_stock_custom_tags.py
mytester/__init__.py
mytester/asgi.py
mytester/settings.py
mytester/urls.py
mytester/wsgi.py
django_fav_stock-0.0.4.dist-info/LICENSE
django_fav_stock-0.0.4.dist-info/METADATA
django_fav_stock-0.0.4.dist-info/WHEEL
django_fav_stock-0.0.4.dist-info/top_level.txt
django_fav_stock-0.0.4.dist-info/RECORD
